{
  "active_step_id": null,
  "active_step_index": null,
  "active_step_job_id": null,
  "active_step_kind": null,
  "active_step_status": null,
  "branch_id": null,
  "branch_name": "",
  "execution_run_id": null,
  "generated_at": "2026-06-10T13:45:17.629244+00:00",
  "killed_worker_id": "a9fdb78b1e037faffcfef9c36e7a2bba02336156ecd6488fd58df05407d210cf",
  "recovery_action": "",
  "recovery_severity": "",
  "recovery_step_index": null,
  "restored_worker_replicas": 4,
  "scenario": "merge-during-exec",
  "support_bundle": "",
  "support_bundle_recovery_verified": false,
  "sync_name": ""
}
