{
  "generated_at": "2026-05-27T01:35:16.088769+00:00",
  "sync_ids": [
    46,
    50,
    51
  ],
  "max_polls": 4,
  "interval_seconds": 30,
  "allow_nonterminal": true,
  "include_all_ingestions": false,
  "completed": true,
  "samples": [
    {
      "sampled_at": "2026-05-27T01:26:06.685523+00:00",
      "poll": 1,
      "sync_id": 46,
      "sync_name": "warn-fix-prefix-221958",
      "sync_status": "syncing",
      "execution_run_status": "running",
      "active_step_status": "running",
      "active_step_id": 1731,
      "active_step_job_live": true,
      "active_step_job_id": 910,
      "active_step_attempted_row_count": 0,
      "active_step_applied_row_count": 0,
      "active_step_fetched_row_count": 7346,
      "active_step_created_age_seconds": 79508.712868,
      "active_step_heartbeat_age_seconds": 7.018091,
      "blocking": 0,
      "warnings": 0,
      "suppressed_warnings": 0,
      "errors": 0
    },
    {
      "sampled_at": "2026-05-27T01:26:06.685523+00:00",
      "poll": 1,
      "sync_id": 50,
      "sync_name": "job-audit-full-035333",
      "sync_status": "syncing",
      "execution_run_status": "running",
      "active_step_status": "running",
      "active_step_id": 1938,
      "active_step_job_live": true,
      "active_step_job_id": 916,
      "active_step_attempted_row_count": 0,
      "active_step_applied_row_count": 0,
      "active_step_fetched_row_count": 7346,
      "active_step_created_age_seconds": 77349.718445,
      "active_step_heartbeat_age_seconds": 19.802254,
      "blocking": 0,
      "warnings": 0,
      "suppressed_warnings": 0,
      "errors": 0
    },
    {
      "sampled_at": "2026-05-27T01:26:06.685523+00:00",
      "poll": 1,
      "sync_id": 51,
      "sync_name": "warn-proof-ipam-232909",
      "sync_status": "syncing",
      "execution_run_status": "running",
      "active_step_status": "running",
      "active_step_id": 2237,
      "active_step_job_live": true,
      "active_step_job_id": 914,
      "active_step_attempted_row_count": 0,
      "active_step_applied_row_count": 0,
      "active_step_fetched_row_count": 7346,
      "active_step_created_age_seconds": 75455.651428,
      "active_step_heartbeat_age_seconds": 0.049922,
      "blocking": 0,
      "warnings": 0,
      "suppressed_warnings": 0,
      "errors": 0
    },
    {
      "sampled_at": "2026-05-27T01:28:32.719599+00:00",
      "poll": 2,
      "sync_id": 46,
      "sync_name": "warn-fix-prefix-221958",
      "sync_status": "syncing",
      "execution_run_status": "running",
      "active_step_status": "running",
      "active_step_id": 1731,
      "active_step_job_live": true,
      "active_step_job_id": 910,
      "active_step_attempted_row_count": 0,
      "active_step_applied_row_count": 0,
      "active_step_fetched_row_count": 7346,
      "active_step_created_age_seconds": 79654.94153,
      "active_step_heartbeat_age_seconds": 3.153159,
      "blocking": 0,
      "warnings": 0,
      "suppressed_warnings": 0,
      "errors": 0
    },
    {
      "sampled_at": "2026-05-27T01:28:32.719599+00:00",
      "poll": 2,
      "sync_id": 50,
      "sync_name": "job-audit-full-035333",
      "sync_status": "syncing",
      "execution_run_status": "running",
      "active_step_status": "running",
      "active_step_id": 1938,
      "active_step_job_live": true,
      "active_step_job_id": 916,
      "active_step_attempted_row_count": 0,
      "active_step_applied_row_count": 0,
      "active_step_fetched_row_count": 7346,
      "active_step_created_age_seconds": 77495.519442,
      "active_step_heartbeat_age_seconds": 15.45916,
      "blocking": 0,
      "warnings": 0,
      "suppressed_warnings": 0,
      "errors": 0
    },
    {
      "sampled_at": "2026-05-27T01:28:32.719599+00:00",
      "poll": 2,
      "sync_id": 51,
      "sync_name": "warn-proof-ipam-232909",
      "sync_status": "syncing",
      "execution_run_status": "running",
      "active_step_status": "running",
      "active_step_id": 2237,
      "active_step_job_live": true,
      "active_step_job_id": 914,
      "active_step_attempted_row_count": 0,
      "active_step_applied_row_count": 0,
      "active_step_fetched_row_count": 7346,
      "active_step_created_age_seconds": 75600.978983,
      "active_step_heartbeat_age_seconds": 25.272586,
      "blocking": 0,
      "warnings": 0,
      "suppressed_warnings": 0,
      "errors": 0
    },
    {
      "sampled_at": "2026-05-27T01:30:57.733911+00:00",
      "poll": 3,
      "sync_id": 46,
      "sync_name": "warn-fix-prefix-221958",
      "sync_status": "syncing",
      "execution_run_status": "running",
      "active_step_status": "running",
      "active_step_id": 1731,
      "active_step_job_live": true,
      "active_step_job_id": 910,
      "active_step_attempted_row_count": 0,
      "active_step_applied_row_count": 0,
      "active_step_fetched_row_count": 7346,
      "active_step_created_age_seconds": 79799.658506,
      "active_step_heartbeat_age_seconds": 27.790719,
      "blocking": 0,
      "warnings": 0,
      "suppressed_warnings": 0,
      "errors": 0
    },
    {
      "sampled_at": "2026-05-27T01:30:57.733911+00:00",
      "poll": 3,
      "sync_id": 50,
      "sync_name": "job-audit-full-035333",
      "sync_status": "syncing",
      "execution_run_status": "running",
      "active_step_status": "running",
      "active_step_id": 1938,
      "active_step_job_live": true,
      "active_step_job_id": 916,
      "active_step_attempted_row_count": 0,
      "active_step_applied_row_count": 0,
      "active_step_fetched_row_count": 7346,
      "active_step_created_age_seconds": 77640.207131,
      "active_step_heartbeat_age_seconds": 10.010613,
      "blocking": 0,
      "warnings": 0,
      "suppressed_warnings": 0,
      "errors": 0
    },
    {
      "sampled_at": "2026-05-27T01:30:57.733911+00:00",
      "poll": 3,
      "sync_id": 51,
      "sync_name": "warn-proof-ipam-232909",
      "sync_status": "syncing",
      "execution_run_status": "running",
      "active_step_status": "running",
      "active_step_id": 2237,
      "active_step_job_live": true,
      "active_step_job_id": 914,
      "active_step_attempted_row_count": 0,
      "active_step_applied_row_count": 0,
      "active_step_fetched_row_count": 7346,
      "active_step_created_age_seconds": 75745.659122,
      "active_step_heartbeat_age_seconds": 19.839503,
      "blocking": 0,
      "warnings": 0,
      "suppressed_warnings": 0,
      "errors": 0
    },
    {
      "sampled_at": "2026-05-27T01:33:22.240577+00:00",
      "poll": 4,
      "sync_id": 46,
      "sync_name": "warn-fix-prefix-221958",
      "sync_status": "syncing",
      "execution_run_status": "running",
      "active_step_status": "running",
      "active_step_id": 1731,
      "active_step_job_live": true,
      "active_step_job_id": 910,
      "active_step_attempted_row_count": 0,
      "active_step_applied_row_count": 0,
      "active_step_fetched_row_count": 7346,
      "active_step_created_age_seconds": 79944.118041,
      "active_step_heartbeat_age_seconds": 22.127942,
      "blocking": 0,
      "warnings": 0,
      "suppressed_warnings": 0,
      "errors": 0
    },
    {
      "sampled_at": "2026-05-27T01:33:22.240577+00:00",
      "poll": 4,
      "sync_id": 50,
      "sync_name": "job-audit-full-035333",
      "sync_status": "syncing",
      "execution_run_status": "running",
      "active_step_status": "running",
      "active_step_id": 1938,
      "active_step_job_live": true,
      "active_step_job_id": 916,
      "active_step_attempted_row_count": 0,
      "active_step_applied_row_count": 0,
      "active_step_fetched_row_count": 7346,
      "active_step_created_age_seconds": 77784.863124,
      "active_step_heartbeat_age_seconds": 4.438703,
      "blocking": 0,
      "warnings": 0,
      "suppressed_warnings": 0,
      "errors": 0
    },
    {
      "sampled_at": "2026-05-27T01:33:22.240577+00:00",
      "poll": 4,
      "sync_id": 51,
      "sync_name": "warn-proof-ipam-232909",
      "sync_status": "syncing",
      "execution_run_status": "running",
      "active_step_status": "running",
      "active_step_id": 2237,
      "active_step_job_live": true,
      "active_step_job_id": 914,
      "active_step_attempted_row_count": 0,
      "active_step_applied_row_count": 0,
      "active_step_fetched_row_count": 7346,
      "active_step_created_age_seconds": 75889.605243,
      "active_step_heartbeat_age_seconds": 13.65022,
      "blocking": 0,
      "warnings": 0,
      "suppressed_warnings": 0,
      "errors": 0
    }
  ],
  "recovery_actions": []
}
